auto_tensorflow/tfa.py
auto_tensorflow-1.3.4.dist-info/LICENSE
auto_tensorflow-1.3.4.dist-info/METADATA
auto_tensorflow-1.3.4.dist-info/WHEEL
auto_tensorflow-1.3.4.dist-info/top_level.txt
auto_tensorflow-1.3.4.dist-info/RECORD
