Metadata-Version: 2.1
Name: auto-tensorflow
Version: 1.3.4
Summary: Build Low Code Automated Tensorflow, What-IF explainable models in just 3 lines of code. To make Deep Learning on Tensorflow absolutely easy for the masses with its low code framework and also increase trust on ML models through What-IF model explainability.
Home-page: https://github.com/rafiqhasan/auto-tensorflow
Author: Hasan Rafiq
License: Apache License 2.0
Classifier: Programming Language :: Python :: 3
Classifier: Operating System :: OS Independent
License-File: LICENSE
Requires-Dist: keras-tuner (==1.0.4)
Requires-Dist: tensorflow-text (==2.6.0)
Requires-Dist: tfx (==1.4.0)
Requires-Dist: witwidget (==1.8.0)
Requires-Dist: tensorflow (==2.6.2)
Requires-Dist: tensorflow-hub (==0.12.0)
Requires-Dist: tensorflow-metadata (==1.4.0)
Requires-Dist: ipython (==7.29.0)
Requires-Dist: tensorflow-estimator (==2.6.0)
Requires-Dist: joblib (==0.14.1)
Requires-Dist: tensorboard-plugin-wit (==1.8.0)
Requires-Dist: tensorboard-data-server (==0.6.1)
Requires-Dist: google-api-core (==1.31.4)
Requires-Dist: google-cloud-aiplatform (==1.10.0)
Requires-Dist: google-cloud (==0.34.0)
Requires-Dist: apache-beam (==2.34.0)
Requires-Dist: protobuf (==3.19.5)
Requires-Dist: jupyterlab-widgets (==3.0.3)
Requires-Dist: PyYAML (==5.4.1)
Requires-Dist: pytz (==2022.6)
Requires-Dist: tensorflow-model-analysis (==0.35.0)
Requires-Dist: tensorflow-data-validation (==1.4.0)
Requires-Dist: tensorboard (==2.6.0)
Requires-Dist: six (==1.15.0)
Requires-Dist: requests (==2.28.1)
Requires-Dist: widgetsnbextension (==3.6.1)
